{"species":{"id":["CHSP"],"idnext":["CLSW"],"idprevious":["CEDW"],"scientific":["Spizella passerina"],"english":["Chipping Sparrow"],"french":["Bruant familier"],"family":["Emberizidae"],"show":[true]},"popsize":[{"region":"Canada","abundance":{"estimate":108.5171,"lower":105.4325,"upper":110.434},"density":{"estimate":0.1566,"lower":0.1522,"upper":0.1594},"areakmsq":6.21},{"region":"4 Northwestern Interior Forest","abundance":{"estimate":13.3838,"lower":12.5532,"upper":14.1742},"density":{"estimate":0.1984,"lower":0.1861,"upper":0.2101},"areakmsq":0.546},{"region":"5 Northern Pacific Rainforest","abundance":{"estimate":1.6434,"lower":1.4761,"upper":1.7322},"density":{"estimate":0.0899,"lower":0.0807,"upper":0.0948},"areakmsq":0.136},{"region":"9 Great Basin","abundance":{"estimate":2.043,"lower":1.9633,"upper":2.1672},"density":{"estimate":0.34,"lower":0.3268,"upper":0.3607},"areakmsq":0.0552},{"region":"10 Northern Rockies","abundance":{"estimate":12.065,"lower":11.6607,"upper":12.4887},"density":{"estimate":0.2821,"lower":0.2727,"upper":0.292},"areakmsq":0.372},{"region":"11 Prairie Potholes","abundance":{"estimate":3.2071,"lower":3.0667,"upper":3.3699},"density":{"estimate":0.0702,"lower":0.0672,"upper":0.0738},"areakmsq":0.444},{"region":"12 Boreal Hardwood Transition","abundance":{"estimate":6.5962,"lower":6.3673,"upper":6.8027},"density":{"estimate":0.1637,"lower":0.158,"upper":0.1688},"areakmsq":0.373},{"region":"13 Lower Great Lakes/St. Lawrence Plain","abundance":{"estimate":3.0125,"lower":2.8545,"upper":3.1568},"density":{"estimate":0.2554,"lower":0.242,"upper":0.2676},"areakmsq":0.102},{"region":"14 Atlantic Northern Forest","abundance":{"estimate":2.2504,"lower":2.1872,"upper":2.3473},"density":{"estimate":0.115,"lower":0.1118,"upper":0.1199},"areakmsq":0.195},{"region":"6-0 Boreal Taiga Plains, South","abundance":{"estimate":18.5299,"lower":18.072,"upper":18.9373},"density":{"estimate":0.2235,"lower":0.218,"upper":0.2284},"areakmsq":0.756},{"region":"6-1 Boreal Taiga Plains, North","abundance":{"estimate":14.1772,"lower":13.381,"upper":15.2519},"density":{"estimate":0.2859,"lower":0.2699,"upper":0.3076},"areakmsq":0.428},{"region":"7-0 Taiga Shield & Hudson Plains, West","abundance":{"estimate":9.6904,"lower":8.5308,"upper":10.5016},"density":{"estimate":0.1489,"lower":0.1311,"upper":0.1614},"areakmsq":0.561},{"region":"7-1 Taiga Shield & Hudson Plains, East","abundance":{"estimate":2.1461,"lower":1.6055,"upper":2.5464},"density":{"estimate":0.0212,"lower":0.0158,"upper":0.0251},"areakmsq":0.925},{"region":"8-0 Boreal Softwood Shield, West","abundance":{"estimate":10.5409,"lower":10.0219,"upper":11.1523},"density":{"estimate":0.2545,"lower":0.242,"upper":0.2693},"areakmsq":0.348},{"region":"8-1 Boreal Softwood Shield, Ontario","abundance":{"estimate":7.4181,"lower":6.9136,"upper":7.7526},"density":{"estimate":0.1715,"lower":0.1599,"upper":0.1793},"areakmsq":0.395},{"region":"8-2 Boreal Softwood Shield, East","abundance":{"estimate":2.338,"lower":2.1826,"upper":2.5122},"density":{"estimate":0.0458,"lower":0.0427,"upper":0.0492},"areakmsq":0.473},{"region":"8-3 Boreal Softwood Shield, Newfoundland","abundance":{"estimate":0.0613,"lower":0.029,"upper":0.0968},"density":{"estimate":0.006,"lower":0.0029,"upper":0.0095},"areakmsq":0.0945}],"densplot":[{"region":"Canada","data":{"landcover":["Conifer","Taiga Conifer","Deciduous","Mixedwood","Shrub","Grass","Arctic Shrub","Arctic Grass","Wetland","Cropland"],"estimate":[0.053,0.0128,0.0107,0.0258,0.0146,0.0053,0.0016,0.0064,0.0086,0.0086],"lower":[0.0515,0.0122,0.0105,0.025,0.0142,0.0052,0.0014,0.0059,0.0081,0.0085],"upper":[0.0538,0.0136,0.0109,0.0264,0.0149,0.0054,0.0017,0.0068,0.0089,0.0089]}},{"region":"4","data":{"landcover":["Conifer","Taiga Conifer","Deciduous","Mixedwood","Shrub","Grass","Arctic Shrub","Arctic Grass","Wetland","Cropland"],"estimate":[0.221,0.2009,0.2115,0.2133,0.198,0.1967,0.1961,0.1856,0.2242,0.2172],"lower":[0.2121,0.1875,0.1975,0.2029,0.1832,0.184,0.1858,0.1729,0.2149,0.1997],"upper":[0.2368,0.2138,0.2278,0.2301,0.2101,0.2064,0.2059,0.1975,0.2338,0.2345]}},{"region":"5","data":{"landcover":["Conifer","Taiga Conifer","Deciduous","Mixedwood","Shrub","Grass","Arctic Shrub","Arctic Grass","Wetland","Cropland"],"estimate":[0.1089,0.1177,0.1083,0.1055,0.1094,0.1101,0.0794,0.1036,0.1095,0.1115],"lower":[0.0976,0.1021,0.097,0.0943,0.0978,0.0985,0.07,0.093,0.0979,0.1013],"upper":[0.1142,0.1309,0.114,0.112,0.1152,0.116,0.0854,0.1114,0.1159,0.124]}},{"region":"9","data":{"landcover":["Conifer","Deciduous","Mixedwood","Shrub","Grass","Arctic Grass","Wetland","Cropland"],"estimate":[0.3416,0.3386,0.2267,0.3943,0.3581,0.2247,0.3449,0.3454],"lower":[0.3276,0.3192,0.2087,0.3797,0.3403,0.2039,0.3239,0.3163],"upper":[0.3613,0.3546,0.2431,0.4199,0.3859,0.2516,0.3727,0.3668]}},{"region":"10","data":{"landcover":["Conifer","Deciduous","Mixedwood","Shrub","Grass","Arctic Grass","Wetland","Cropland"],"estimate":[0.3052,0.2812,0.2988,0.313,0.2658,0.2544,0.3064,0.1795],"lower":[0.2943,0.2686,0.2911,0.2992,0.2594,0.2425,0.298,0.1714],"upper":[0.3154,0.2926,0.3103,0.322,0.2782,0.2656,0.3168,0.1891]}},{"region":"11","data":{"landcover":["Conifer","Deciduous","Mixedwood","Shrub","Grass","Arctic Grass","Wetland","Cropland"],"estimate":[0.1207,0.0997,0.1346,0.0754,0.0729,0,0.0796,0.0694],"lower":[0.1142,0.0935,0.1252,0.072,0.0685,0,0.0766,0.066],"upper":[0.1293,0.1052,0.1423,0.0803,0.0769,0,0.086,0.0724]}},{"region":"12","data":{"landcover":["Conifer","Deciduous","Mixedwood","Shrub","Grass","Arctic Shrub","Arctic Grass","Wetland","Cropland"],"estimate":[0.1609,0.1907,0.1699,0.1796,0.1782,0,0,0.1738,0.1971],"lower":[0.1549,0.1812,0.1649,0.1714,0.1698,0,0,0.1672,0.1839],"upper":[0.1663,0.1963,0.1765,0.187,0.1847,0,0,0.1806,0.2032]}},{"region":"13","data":{"landcover":["Conifer","Deciduous","Mixedwood","Shrub","Grass","Arctic Shrub","Arctic Grass","Wetland","Cropland"],"estimate":[0.1889,0.2741,0.2269,0.2774,0.2693,0,0,0.2382,0.2792],"lower":[0.182,0.2609,0.2189,0.2612,0.2556,0,0,0.2256,0.2619],"upper":[0.1959,0.2865,0.2368,0.2904,0.2832,0,0,0.25,0.2925]}},{"region":"14","data":{"landcover":["Conifer","Deciduous","Mixedwood","Shrub","Grass","Arctic Shrub","Arctic Grass","Wetland","Cropland"],"estimate":[0.1021,0.1216,0.1085,0.1154,0.1186,0,0,0.1106,0.1617],"lower":[0.0969,0.1178,0.1054,0.1111,0.1147,0,0,0.1076,0.1539],"upper":[0.106,0.1273,0.1132,0.1207,0.1234,0,0,0.1157,0.1717]}},{"region":"6-0","data":{"landcover":["Conifer","Taiga Conifer","Deciduous","Mixedwood","Shrub","Grass","Arctic Grass","Wetland","Cropland"],"estimate":[0.2912,0.2642,0.1956,0.2599,0.2537,0.2345,0.2815,0.281,0.1323],"lower":[0.2831,0.2499,0.1879,0.253,0.2361,0.2279,0.2681,0.2709,0.1292],"upper":[0.3006,0.2833,0.2023,0.2678,0.2637,0.2419,0.2941,0.2918,0.1355]}},{"region":"6-1","data":{"landcover":["Conifer","Taiga Conifer","Deciduous","Mixedwood","Shrub","Grass","Arctic Shrub","Arctic Grass","Wetland"],"estimate":[0.3786,0.3217,0.3237,0.3207,0.2991,0.3187,0.2203,0.2193,0.3695],"lower":[0.3545,0.3006,0.3099,0.3072,0.28,0.2987,0.2027,0.1959,0.3513],"upper":[0.4016,0.3509,0.3519,0.3427,0.3327,0.3587,0.2483,0.2452,0.4051]}},{"region":"7-0","data":{"landcover":["Conifer","Taiga Conifer","Deciduous","Mixedwood","Shrub","Grass","Arctic Shrub","Arctic Grass","Wetland","Cropland"],"estimate":[0.2041,0.1887,0.1967,0.1613,0.1819,0.2086,0.131,0.1264,0.1433,0],"lower":[0.1837,0.1698,0.1814,0.1427,0.1621,0.1857,0.1109,0.1043,0.123,0],"upper":[0.2201,0.2085,0.2189,0.1827,0.1972,0.2275,0.1432,0.1373,0.157,0]}},{"region":"7-1","data":{"landcover":["Conifer","Taiga Conifer","Deciduous","Mixedwood","Shrub","Grass","Arctic Shrub","Arctic Grass","Wetland","Cropland"],"estimate":[0.0215,0.0207,0.0279,0.0261,0.021,0.0195,0.0187,0.0181,0.0354,0.0194],"lower":[0.0166,0.0158,0.0188,0.0187,0.0159,0.015,0.0141,0.0138,0.0203,0.0143],"upper":[0.0261,0.0241,0.0333,0.0316,0.0245,0.0238,0.0232,0.0229,0.0429,0.0231]}},{"region":"8-0","data":{"landcover":["Conifer","Taiga Conifer","Deciduous","Mixedwood","Shrub","Grass","Arctic Grass","Wetland","Cropland"],"estimate":[0.3036,0.2846,0.2548,0.2972,0.2554,0.2601,0,0.2887,0.1551],"lower":[0.2891,0.251,0.2323,0.2798,0.2325,0.2338,0,0.2685,0.1398],"upper":[0.3218,0.3147,0.2731,0.3124,0.2814,0.2841,0,0.3145,0.1716]}},{"region":"8-1","data":{"landcover":["Conifer","Taiga Conifer","Deciduous","Mixedwood","Shrub","Grass","Arctic Grass","Wetland","Cropland"],"estimate":[0.1817,0.1683,0.1857,0.1837,0.1874,0.1901,0,0.1803,0.1918],"lower":[0.1682,0.1508,0.1775,0.1735,0.173,0.177,0,0.1663,0.1776],"upper":[0.1916,0.1888,0.1952,0.1949,0.1999,0.2019,0,0.1929,0.2012]}},{"region":"8-2","data":{"landcover":["Conifer","Taiga Conifer","Deciduous","Mixedwood","Shrub","Grass","Arctic Shrub","Arctic Grass","Wetland","Cropland"],"estimate":[0.0443,0.0442,0.0651,0.0506,0.046,0.0478,0.045,0,0.0504,0.1618],"lower":[0.041,0.0407,0.0619,0.048,0.0427,0.0445,0.0414,0,0.0472,0.1504],"upper":[0.0483,0.0484,0.0681,0.0542,0.05,0.0516,0.0492,0,0.0538,0.173]}},{"region":"8-3","data":{"landcover":["Conifer","Taiga Conifer","Deciduous","Mixedwood","Shrub","Grass","Arctic Shrub","Wetland","Cropland"],"estimate":[0.0062,0.0064,0.0064,0.0064,0.0064,0.0063,0.0064,0.0064,0.0064],"lower":[0.0029,0.003,0.003,0.003,0.003,0.003,0.003,0.003,0.003],"upper":[0.0097,0.0101,0.01,0.01,0.01,0.01,0.0101,0.01,0.0101]}}]}
